sanbomics/__init__.py
sanbomics/plots.py
sanbomics/tools.py
sanbomics/data/human_ids.csv
sanbomics/data/mouse_ids.csv
sanbomics-0.1.0.dist-info/LICENSE
sanbomics-0.1.0.dist-info/METADATA
sanbomics-0.1.0.dist-info/WHEEL
sanbomics-0.1.0.dist-info/top_level.txt
sanbomics-0.1.0.dist-info/RECORD
